fonttoolsWB/__init__.py
fonttoolsWB/gui.py
fonttoolsWB/data/__init__.py
fonttoolsWB/data/application.yml
fonttoolsWB/data/firstRun.py
fonttoolsWB/data/splashscreen.png
fonttoolsWB-0.2.5.dist-info/LICENSE
fonttoolsWB-0.2.5.dist-info/METADATA
fonttoolsWB-0.2.5.dist-info/WHEEL
fonttoolsWB-0.2.5.dist-info/entry_points.txt
fonttoolsWB-0.2.5.dist-info/top_level.txt
fonttoolsWB-0.2.5.dist-info/RECORD
