Metadata-Version: 2.1
Name: fonttoolsWB
Version: 0.2.5
Summary: FontTools WorkBench - Edit OpenType fonts as XML.
Home-page: https://gitlab.com/workbench2/fonttoolsWB
Author: Andreas Eigendorf
License: MIT
Project-URL: Source, https://gitlab.com/workbench2/fonttoolsWB
Project-URL: Documentation, https://workbench2.gitlab.io/fonttoolsWB
Project-URL: Tracker, https://gitlab.com/workbench2/fonttoolsWB/-/issues
Keywords: workbench,wxPython,GUI
Platform: WIN32
Platform: WIN64
Platform: OSX
Platform: POSIX
Classifier: Development Status :: 4 - Beta
Classifier: License :: OSI Approved :: MIT License
Classifier: Operating System :: MacOS
Classifier: Operating System :: Microsoft :: Windows
Classifier: Operating System :: POSIX
Classifier: Environment :: MacOS X :: Cocoa
Classifier: Environment :: Win32 (MS Windows)
Classifier: Environment :: X11 Applications :: GTK
Classifier: Programming Language :: Python :: 3
Classifier: Programming Language :: Python :: 3.8
Classifier: Programming Language :: Python :: 3.9
Classifier: Programming Language :: Python :: 3.10
Classifier: Programming Language :: Python :: 3.11
Classifier: Programming Language :: Python :: 3.12
Classifier: Programming Language :: Python :: Implementation :: CPython
Classifier: Intended Audience :: Developers
Classifier: Intended Audience :: End Users/Desktop
Classifier: Topic :: Text Processing :: Fonts
Classifier: Topic :: Multimedia :: Graphics
Requires-Python: >=3.8
License-File: LICENSE
Requires-Dist: wbBase >=0.2.9
Requires-Dist: wbpFonttools >=0.2.6
Requires-Dist: wbpLoglist >=0.2
Requires-Dist: wbpOutput >=0.2
Requires-Dist: wbpShell >=0.2
Requires-Dist: wbpTextedit >=0.2.2
Requires-Dist: wbpUItools >=0.2
Provides-Extra: develop
Requires-Dist: wbpNamespace >=0.2 ; extra == 'develop'
Requires-Dist: wbpWidgetinspector >=0.2 ; extra == 'develop'
Requires-Dist: wbpHTMLpanel >=0.2.4 ; extra == 'develop'
